Changes.txt
License.txt
MANIFEST.in
README.txt
Readme.txt
setup.py
Documentation/InversionTest.InversionAnalysis-module.html
Documentation/InversionTest.InversionAnalysis-pysrc.html
Documentation/InversionTest.InversionAnalysis.GradedPosetSequence-class.html
Documentation/InversionTest.InversionAnalysis.InvalidGradedPosetError-class.html
Documentation/InversionTest.InversionAnalysis.MissingElementError-class.html
Documentation/InversionTest.InversionDistribution-module.html
Documentation/InversionTest.InversionDistribution-pysrc.html
Documentation/InversionTest.InversionDistribution.InversionCountsCache-class.html
Documentation/InversionTest.MonteCarloSampler-module.html
Documentation/InversionTest.MonteCarloSampler-pysrc.html
Documentation/InversionTest.MonteCarloSampler.MCBMeanDifferenceTest-class.html
Documentation/InversionTest.MonteCarloSampler.MCBStoppingRuleTest-class.html
Documentation/InversionTest.MonteCarloSampler.MCBWilcoxonRankTest-class.html
Documentation/InversionTest.MonteCarloSampler.MCHypothesisTest-class.html
Documentation/InversionTest.MonteCarloSampler.MCMeanDifferenceTest-class.html
Documentation/InversionTest.MonteCarloSampler.MCWilcoxonRankTest-class.html
Documentation/InversionTest.MonteCarloSampler.MonteCarloEstimator-class.html
Documentation/InversionTest.PolynomialOperations-module.html
Documentation/InversionTest.PolynomialOperations-pysrc.html
Documentation/InversionTest.StatisticalTests-module.html
Documentation/InversionTest.StatisticalTests-pysrc.html
Documentation/InversionTest.StatisticalTests.SignTestCancelationError-class.html
Documentation/InversionTest.StatisticalTests.SignTestException-class.html
Documentation/InversionTest.StatisticalTests.SignTestInvalidPairLengthError-class.html
Documentation/InversionTest.StatisticalTests.SystemReseededRandom-class.html
Documentation/api-objects.txt
Documentation/class-tree.html
Documentation/crarr.png
Documentation/epydoc.js
Documentation/frames.html
Documentation/help.html
InversionTest.egg-info/PKG-INFO
InversionTest.egg-info/SOURCES.txt
InversionTest.egg-info/dependency_links.txt
InversionTest.egg-info/top_level.txt
