Metadata-Version: 1.1
Name: InversionTest
Version: 1.2
Summary: Sequence Permutation Similarity and Hypothesis Testing Package
Home-page: https://sites.google.com/site/benjaminnye/
Author: Benjamin D. Nye
Author-email: benjamid@seas.upenn.edu
License: APL 2.0
Keywords: inversion counts statistics software hypothesis testing censored ties
Platform: UNKNOWN
Classifier: License :: OSI Approved :: Apache Software License
Classifier: Programming Language :: Python
Classifier: Development Status :: 5 - Production/Stable
Classifier: Intended Audience :: Science/Research
Classifier: Topic :: Scientific/Engineering :: Mathematics
